PyMELib/EnumerationAlgorithms.py
PyMELib/Factors.py
PyMELib/PreprocessingAlgorithms.py
PyMELib/TreeDecompositions.py
PyMELib/__init__.py
PyMELib/labels.py
PyMELib/labels2.py
PyMELib/utils/__init__.py
PyMELib/utils/addConstraints.py
PyMELib/utils/comb_utils.py
PyMELib/utils/graph_utils.py
PyMELib/utils/labels_utils.py
PyMELib/utils/readHypergraphFromFile.py
pymelib-0.7.1.dist-info/LICENSE
pymelib-0.7.1.dist-info/METADATA
pymelib-0.7.1.dist-info/WHEEL
pymelib-0.7.1.dist-info/top_level.txt
pymelib-0.7.1.dist-info/RECORD
