Metadata-Version: 2.2
Name: PyMELib
Version: 0.7.1
Summary: First version of the PyMELib (Python Minimal Enumeration Library) library
Author: Dan S. Mizrahi and Batya Kenig
Author-email: danmizrahithemiz@gmail.com
Classifier: Programming Language :: Python :: 3
Classifier: License :: OSI Approved :: MIT License
Classifier: Operating System :: OS Independent
Requires-Python: >=3.8
License-File: LICENSE
Requires-Dist: networkx
Requires-Dist: typing
Requires-Dist: frozendict
Requires-Dist: matplotlib
Requires-Dist: EoN
Requires-Dist: plotly
Provides-Extra: test
Requires-Dist: pytest; extra == "test"
Dynamic: author
Dynamic: author-email
Dynamic: classifier
Dynamic: description
Dynamic: description-content-type
Dynamic: provides-extra
Dynamic: requires-dist
Dynamic: requires-python
Dynamic: summary
